ax/__init__.py
ax/py.typed
ax/version.py
ax/adapter/__init__.py
ax/adapter/adapter_utils.py
ax/adapter/base.py
ax/adapter/cross_validation.py
ax/adapter/data_utils.py
ax/adapter/discrete.py
ax/adapter/factory.py
ax/adapter/pairwise.py
ax/adapter/prediction_utils.py
ax/adapter/random.py
ax/adapter/registry.py
ax/adapter/torch.py
ax/adapter/tests/__init__.py
ax/adapter/tests/test_adapter_utils.py
ax/adapter/tests/test_base_adapter.py
ax/adapter/tests/test_cross_validation.py
ax/adapter/tests/test_data_utils.py
ax/adapter/tests/test_discrete_adapter.py
ax/adapter/tests/test_factory.py
ax/adapter/tests/test_hierarchical_search_space.py
ax/adapter/tests/test_model_fit_metrics.py
ax/adapter/tests/test_prediction_utils.py
ax/adapter/tests/test_random_adapter.py
ax/adapter/tests/test_registry.py
ax/adapter/tests/test_robust_adapter.py
ax/adapter/tests/test_torch_adapter.py
ax/adapter/tests/test_torch_moo_adapter.py
ax/adapter/tests/test_transform_utils.py
ax/adapter/tests/test_utils.py
ax/adapter/transforms/__init__.py
ax/adapter/transforms/base.py
ax/adapter/transforms/bilog_y.py
ax/adapter/transforms/cast.py
ax/adapter/transforms/choice_encode.py
ax/adapter/transforms/convert_metric_names.py
ax/adapter/transforms/deprecated_transform_mixin.py
ax/adapter/transforms/derelativize.py
ax/adapter/transforms/fill_missing_parameters.py
ax/adapter/transforms/fixed_to_tunable.py
ax/adapter/transforms/int_range_to_choice.py
ax/adapter/transforms/int_to_float.py
ax/adapter/transforms/ivw.py
ax/adapter/transforms/log.py
ax/adapter/transforms/log_y.py
ax/adapter/transforms/logit.py
ax/adapter/transforms/map_key_to_float.py
ax/adapter/transforms/merge_repeated_measurements.py
ax/adapter/transforms/metadata_to_float.py
ax/adapter/transforms/metadata_to_parameter.py
ax/adapter/transforms/metadata_to_task.py
ax/adapter/transforms/metrics_as_task.py
ax/adapter/transforms/one_hot.py
ax/adapter/transforms/power_transform_y.py
ax/adapter/transforms/relativize.py
ax_platform-1.1.2.dist-info/licenses/LICENSE
ax_platform-1.1.2.dist-info/METADATA
ax_platform-1.1.2.dist-info/WHEEL
ax_platform-1.1.2.dist-info/top_level.txt
ax_platform-1.1.2.dist-info/RECORD
