Metadata-Version: 2.4
Name: ax-platform
Version: 1.1.2
Summary: Adaptive Experimentation
Author: Meta Platforms, Inc.
License-Expression: MIT
Project-URL: Homepage, https://ax.dev/
Project-URL: Repository, https://github.com/facebook/Ax
Keywords: Experimentation,Optimization
Classifier: Development Status :: 5 - Production/Stable
Classifier: Operating System :: POSIX :: Linux
Classifier: Operating System :: MacOS :: MacOS X
Classifier: Programming Language :: Python :: 3
Requires-Python: >=3.10
License-File: LICENSE
Requires-Dist: botorch[pymoo]>=0.15.1
Requires-Dist: jinja2
Requires-Dist: pandas
Requires-Dist: scipy
Requires-Dist: scikit-learn
Requires-Dist: ipywidgets
Requires-Dist: plotly>=5.12.0
Requires-Dist: pyre-extensions
Requires-Dist: sympy
Requires-Dist: markdown
Provides-Extra: dev
Requires-Dist: beautifulsoup4; extra == "dev"
Requires-Dist: Jinja2; extra == "dev"
Requires-Dist: pyfakefs; extra == "dev"
Requires-Dist: pytest>=4.6; extra == "dev"
Requires-Dist: pytest-cov; extra == "dev"
Requires-Dist: sphinx; extra == "dev"
Requires-Dist: sphinx-autodoc-typehints; extra == "dev"
Requires-Dist: sphinx_rtd_theme; extra == "dev"
Requires-Dist: lxml; extra == "dev"
Requires-Dist: mdformat-myst; extra == "dev"
Provides-Extra: mysql
Requires-Dist: SQLAlchemy==1.4.17; extra == "mysql"
Provides-Extra: notebook
Requires-Dist: jupyter; extra == "notebook"
Provides-Extra: unittest-minimal
Requires-Dist: tensorboard>=2.18.0; extra == "unittest-minimal"
Requires-Dist: torchx; extra == "unittest-minimal"
Requires-Dist: pyarrow; extra == "unittest-minimal"
Requires-Dist: xgboost>=3.0.2; extra == "unittest-minimal"
Provides-Extra: unittest
Requires-Dist: ax-platform[dev,mysql,notebook,unittest_minimal]; extra == "unittest"
Provides-Extra: tutorial
Requires-Dist: ax-platform[unittest]; extra == "tutorial"
Requires-Dist: matplotlib; extra == "tutorial"
Requires-Dist: papermill; extra == "tutorial"
Requires-Dist: mdformat; extra == "tutorial"
Dynamic: license-file
